cmoncrawl/aggregator/__init__.py
cmoncrawl/aggregator/index_query.py
cmoncrawl/aggregator/utils/__init__.py
cmoncrawl/aggregator/utils/helpers.py
cmoncrawl/aggregator/utils/ndjson_decoder.py
cmoncrawl/common/loggers.py
cmoncrawl/common/types.py
cmoncrawl/integrations/commands.py
cmoncrawl/middleware/artemis.py
cmoncrawl/middleware/synchronized.py
cmoncrawl/processor/__init__.py
cmoncrawl/processor/extraction/filters.py
cmoncrawl/processor/extraction/utils.py
cmoncrawl/processor/pipeline/downloader.py
cmoncrawl/processor/pipeline/extractor.py
cmoncrawl/processor/pipeline/pipeline.py
cmoncrawl/processor/pipeline/router.py
cmoncrawl/processor/pipeline/streamer.py
Common_Crawl_Extractor-0.8.0.dist-info/LICENSE
Common_Crawl_Extractor-0.8.0.dist-info/METADATA
Common_Crawl_Extractor-0.8.0.dist-info/WHEEL
Common_Crawl_Extractor-0.8.0.dist-info/top_level.txt
Common_Crawl_Extractor-0.8.0.dist-info/RECORD
