Metadata-Version: 2.1
Name: Common-Crawl-Extractor
Version: 0.8.0
Project-URL: Source, https://github.com/hynky1999/Rocnikovy-Projekt
Keywords: Common Crawl,Crawl,Extractor,Common Crawl Extractor,Web Crawler,Web Extractor,Web Scraper
Classifier: Development Status :: 3 - Alpha
Classifier: License :: OSI Approved :: MIT License
Classifier: Programming Language :: Python :: 3
Classifier: Programming Language :: Python :: 3.10
License-File: LICENSE
Requires-Dist: aiofiles (==0.8.0)
Requires-Dist: aiohttp (==3.8.1)
Requires-Dist: aiosignal (==1.2.0)
Requires-Dist: async-timeout (==4.0.2)
Requires-Dist: attrs (==21.4.0)
Requires-Dist: beautifulsoup4 (==4.11.1)
Requires-Dist: bs4 (==0.0.1)
Requires-Dist: charset-normalizer (==2.1.0)
Requires-Dist: docopt (==0.6.2)
Requires-Dist: frozenlist (==1.3.0)
Requires-Dist: idna (==3.3)
Requires-Dist: multidict (==6.0.2)
Requires-Dist: six (==1.16.0)
Requires-Dist: soupsieve (==2.3.2.post1)
Requires-Dist: stomp.py (==8.0.1)
Requires-Dist: warcio (==1.7.4)
Requires-Dist: yarl (==1.7.2)
